RING COUNTER/md.v
module Ring_Counter #(parameter WIDTH=4) 
//Parameter width stores the size bits of the output in the ring counter....
(  
  	input clk,                
	input reset,
  	output reg [WIDTH-1:0] out
);    

//We always begin our operations at the negative edge of the clock...

always @ (negedge clk) 
begin
	//Output is 1 if not performing reset....
    if (!reset)
        out <= 1;
    else 
	begin
        out[WIDTH-1] <= out[0];
    	for (integer i = 0; i < WIDTH-1; i=i+1) 
		begin
        	out[i] <= out[i+1];
			//Here the output is shown for the shifting of the 1's in the ring counter...
    	end
    end
end
endmodule

RING COUNTER/tb.v
//TESTBENCH FILE FOR RING COUNTER......

module tb;
parameter WIDTH = 4;
  
//Instantiating the variables from the module file...
reg clk;
reg reset;
wire [WIDTH-1:0] out;

//Dumping the modules and the values for the ouput in terminal and gtkwave...
Ring_Counter RC (.clk (clk),.reset (reset),.out (out));
  
always #10 clk = ~clk;
//Clock always in the continuous interval of 10 ps...
  
initial 
begin
    //Initializing the values...
	{clk, reset} <= 0;
    $monitor ("T=%0t out=%b", $time, out);
    //For displaying the output in terminal...
    repeat (2) @(negedge clk);
    //At every 2 intervals of clock we see the change in the counter along with the manipulation of reset...
    reset <= 1;
    repeat (15) @(negedge clk);
    //For displaying in 15 iterations...
    $finish;
end
  
initial 
begin
    //This is done for the output in gtkwave...
    $dumpfile("RING_COUNTER.vcd");
    $dumpvars(0,tb);
end
endmodule

RING COUNTER/RING_COUNTER.vcd
$date
	Tue Nov 23 13:20:30 2021
$end
$version
	Icarus Verilog
$end
$timescale
	1s
$end
$scope module tb $end
$var wire 4 ! out [3:0] $end
$var reg 1 " clk $end
$var reg 1 # reset $end
$scope module RC $end
$var wire 1 " clk $end
$var wire 1 # reset $end
$var reg 4 $ out [3:0] $end
$scope begin $ivl_for_loop0 $end
$var integer 32 % i [31:0] $end
$upscope $end
$upscope $end
$upscope $end
$enddefinitions $end
#0
$dumpvars
bx %
b1 $
0#
0"
b1 !
$end
#10
1"
#20
1#
0"
#30
1"
#40
b1000 !
b1000 $
b11 %
0"
#50
1"
#60
b100 !
b100 $
b11 %
0"
#70
1"
#80
b10 !
b10 $
b11 %
0"
#90
1"
#100
b1 !
b1 $
b11 %
0"
#110
1"
#120
b1000 !
b1000 $
b11 %
0"
#130
1"
#140
b100 !
b100 $
b11 %
0"
#150
1"
#160
b10 !
b10 $
b11 %
0"
#170
1"
#180
b1 !
b1 $
b11 %
0"
#190
1"
#200
b1000 !
b1000 $
b11 %
0"
#210
1"
#220
b100 !
b100 $
b11 %
0"
#230
1"
#240
b10 !
b10 $
b11 %
0"
#250
1"
#260
b1 !
b1 $
b11 %
0"
#270
1"
#280
b1000 !
b1000 $
b11 %
0"
#290
1"
#300
b100 !
b100 $
b11 %
0"
#310
1"
#320
b10 !
b10 $
b11 %
0"
